libname/__init__.py
libname/mos.py
MosqitoMod-0.0.2.dist-info/METADATA
MosqitoMod-0.0.2.dist-info/WHEEL
MosqitoMod-0.0.2.dist-info/top_level.txt
MosqitoMod-0.0.2.dist-info/RECORD
